examples/__init__.py
examples/cifar10.py
ezdl/__init__.py
ezdl/__main__.py
ezdl/callbacks.py
ezdl/cli.py
ezdl/complexity.py
ezdl/data.py
ezdl/loss.py
ezdl/metrics.py
ezdl/scheduler.py
ezdl/transforms.py
ezdl/wandb_manip.py
ezdl/app/__init__.py
ezdl/app/gui.py
ezdl/app/gui_old.py
ezdl/app/guicli.py
ezdl/app/inference.py
ezdl/app/markdown.py
ezdl/app/utils.py
ezdl/datasets/__init__.py
ezdl/datasets/weedmap/__init__.py
ezdl/datasets/weedmap/rededge_stats.py
ezdl/datasets/weedmap/sequoia_stats.py
ezdl/datasets/weedmap/weedmap.py
ezdl/experiment/__init__.py
ezdl/experiment/experiment.py
ezdl/experiment/ez_trainer.py
ezdl/experiment/kd_ez_trainer.py
ezdl/experiment/kd_seg_trainer.py
ezdl/experiment/parameters.py
ezdl/experiment/resume.py
ezdl/experiment/run.py
ezdl/experiment/seg_trainer.py
ezdl/logger/__init__.py
ezdl/logger/basesg_logger.py
ezdl/logger/clearml_logger.py
ezdl/logger/text_logger.py
ezdl/logger/wandb_logger.py
ezdl/models/__init__.py
ezdl/models/base.py
ezdl/models/bisenetv1.py
ezdl/models/bisenetv2.py
ezdl/models/custom_cnn.py
ezdl/models/custom_vit.py
ezdl/models/ddrnet.py
ezdl/models/deeplab.py
ezdl/models/dummy.py
ezdl/models/fchardnet.py
ezdl/models/fcn.py
ezdl/models/lawin.py
ezdl/models/regseg.py
ezdl/models/segformer.py
ezdl/models/segnet.py
ezdl/models/sfnet.py
ezdl/models/backbones/__init__.py
ezdl/models/backbones/convnext.py
ezdl/models/backbones/micronet.py
ezdl/models/backbones/mit.py
ezdl/models/backbones/mobilenetv2.py
ezdl/models/backbones/mobilenetv3.py
ezdl/models/backbones/poolformer.py
ezdl/models/backbones/pvt.py
ezdl/models/backbones/resnet.py
ezdl/models/backbones/resnetd.py
ezdl/models/backbones/rest.py
ezdl/models/backbones/uniformer.py
ezdl/models/heads/__init__.py
ezdl/models/heads/condnet.py
ezdl/models/heads/fapn.py
ezdl/models/heads/fcn.py
ezdl/models/heads/fpn.py
ezdl/models/heads/laweed.py
ezdl/models/heads/lawin.py
ezdl/models/heads/segformer.py
ezdl/models/heads/sfnet.py
ezdl/models/heads/upernet.py
ezdl-0.0.7.dist-info/LICENSE
ezdl-0.0.7.dist-info/METADATA
ezdl-0.0.7.dist-info/WHEEL
ezdl-0.0.7.dist-info/entry_points.txt
ezdl-0.0.7.dist-info/top_level.txt
ezdl-0.0.7.dist-info/RECORD
