Metadata-Version: 2.1
Name: ezdl
Version: 0.0.7
Summary: A Simple Tool to make Deep Learning projects easier
Home-page: https://github.com/pasqualedem/EzDL
Author: Pasquale De Marinis
Author-email: pas.demarinis@gmail.com
Classifier: Programming Language :: Python :: 3
Classifier: License :: OSI Approved :: MIT License
Classifier: Operating System :: OS Independent
Requires-Python: >=3.7
License-File: LICENSE
Requires-Dist: adjectiveanimalnumber
Requires-Dist: click
Requires-Dist: codecarbon
Requires-Dist: matplotlib
Requires-Dist: numpy
Requires-Dist: opencv-python
Requires-Dist: plotly
Requires-Dist: Pillow
Requires-Dist: ptflops
Requires-Dist: ruamel.yaml
Requires-Dist: scipy
Requires-Dist: super-gradients (==3.0.7)
Requires-Dist: torch
Requires-Dist: torchaudio
Requires-Dist: torchmetrics
Requires-Dist: torchvision
Requires-Dist: torchdistill
Requires-Dist: tqdm
Requires-Dist: wandb
Requires-Dist: transformers
Requires-Dist: einops
Requires-Dist: streamlit
Requires-Dist: streamlit-ace
Requires-Dist: easydict
Requires-Dist: clearml
